botpapy/__init__.py
botpapy/botpapy.py
botpapy/color.py
botpapy/config.py
botpapy/crangeTester.py
botpapy/helpers.py
botpapy/image.py
botpapy/match.py
botpapy/rect.py
botpapy/selectWindow.py
botpapy-0.9.7.dist-info/METADATA
botpapy-0.9.7.dist-info/WHEEL
botpapy-0.9.7.dist-info/top_level.txt
botpapy-0.9.7.dist-info/RECORD
