Metadata-Version: 2.4
Name: botpapy
Version: 0.9.7
Summary: Python Library to automate tasks with template matching in (non-visible) windows
Home-page: https://github.com/Alpel99/botpapy
Author: Alpel
Author-email: Alpel@gmx.net
Classifier: Programming Language :: Python :: 3
Classifier: Operating System :: Microsoft :: Windows
Requires-Dist: numpy
Requires-Dist: opencv_python
Requires-Dist: Pillow
Requires-Dist: pywin32
Dynamic: author
Dynamic: author-email
Dynamic: classifier
Dynamic: description
Dynamic: description-content-type
Dynamic: home-page
Dynamic: requires-dist
Dynamic: summary
